README.md
setup.py
geokrety_api_models/__init__.py
geokrety_api_models/badge.py
geokrety_api_models/base.py
geokrety_api_models/geokret.py
geokrety_api_models/move.py
geokrety_api_models/move_comment.py
geokrety_api_models/news.py
geokrety_api_models/news_comment.py
geokrety_api_models/news_subscription.py
geokrety_api_models/user.py
geokrety_api_models.egg-info/PKG-INFO
geokrety_api_models.egg-info/SOURCES.txt
geokrety_api_models.egg-info/dependency_links.txt
geokrety_api_models.egg-info/requires.txt
geokrety_api_models.egg-info/top_level.txt
geokrety_api_models/utilities/__init__.py
geokrety_api_models/utilities/const.py
geokrety_api_models/utilities/date.py
geokrety_api_models/utilities/move_tasks.py
tests/__init__.py
tests/test_badge.py
tests/test_move.py
tests/mixins/__init__.py
tests/mixins/responses_mixin.py
tests/utilities/__init__.py
tests/utilities/test_move_tasks.py