Metadata-Version: 2.1
Name: geokrety-api-models
Version: 0.0.3
Summary: The GeoKrety API ORM
Home-page: https://github.com/geokrety/geokrety-api-models
Author: Mathieu Alorent
Author-email: kumy@geokrety.org
License: UNKNOWN
Platform: UNKNOWN
Classifier: Programming Language :: Python :: 3
Classifier: License :: OSI Approved :: MIT License
Classifier: Operating System :: OS Independent
